PhotExcel/PhotExcel.py
PhotExcel/__init__.py
Photo_Excel-0.0.1.dist-info/LICENSE
Photo_Excel-0.0.1.dist-info/METADATA
Photo_Excel-0.0.1.dist-info/WHEEL
Photo_Excel-0.0.1.dist-info/top_level.txt
Photo_Excel-0.0.1.dist-info/RECORD
