Metadata-Version: 2.1
Name: Photo-Excel
Version: 0.0.1
Summary: Change Photos into a Excel file
Home-page: https://github.com/yagav/PhotExcel
Author: Yagav Akhilesh
Author-email: yagav123456@gmail.com
License: UNKNOWN
Keywords: python,excel,photo converter,photo-excel,photo to excel
Platform: UNKNOWN
Classifier: Programming Language :: Python :: 3
Classifier: Operating System :: OS Independent
Classifier: License :: OSI Approved :: MIT License
License-File: LICENSE
Requires-Dist: numpy
Requires-Dist: pandas
Requires-Dist: pillow
